rc2.py
setup.py
rc2.egg-info/PKG-INFO
rc2.egg-info/SOURCES.txt
rc2.egg-info/dependency_links.txt
rc2.egg-info/top_level.txt